RuanjianshejiDeZhexue/README.md
RuanjianshejiDeZhexue/__init__.py
RuanjianshejiDeZhexue/__main__.py
RuanjianshejiDeZhexue/file.epub
RuanjianshejiDeZhexue/index.html
RuanjianshejiDeZhexue/css/__init__.py
RuanjianshejiDeZhexue/css/annotations.css
RuanjianshejiDeZhexue/css/main.css
RuanjianshejiDeZhexue/css/normalize.css
RuanjianshejiDeZhexue/css/popup.css
RuanjianshejiDeZhexue/font/__init__.py
RuanjianshejiDeZhexue/font/fontello.eot
RuanjianshejiDeZhexue/font/fontello.svg
RuanjianshejiDeZhexue/font/fontello.ttf
RuanjianshejiDeZhexue/font/fontello.woff
RuanjianshejiDeZhexue/img/__init__.py
RuanjianshejiDeZhexue/img/annotator-glyph-sprite.png
RuanjianshejiDeZhexue/img/annotator-icon-sprite.png
RuanjianshejiDeZhexue/img/apple-touch-icon.png
RuanjianshejiDeZhexue/img/cancelfullscreen.png
RuanjianshejiDeZhexue/img/close.png
RuanjianshejiDeZhexue/img/fullscreen.png
RuanjianshejiDeZhexue/img/loader.gif
RuanjianshejiDeZhexue/img/menu-icon.png
RuanjianshejiDeZhexue/img/save.png
RuanjianshejiDeZhexue/img/saved.png
RuanjianshejiDeZhexue/img/settings-s.png
RuanjianshejiDeZhexue/img/settings.png
RuanjianshejiDeZhexue/img/star.png
RuanjianshejiDeZhexue/js/__init__.py
RuanjianshejiDeZhexue/js/epub.js
RuanjianshejiDeZhexue/js/epub.min.js
RuanjianshejiDeZhexue/js/epub.min.map
RuanjianshejiDeZhexue/js/hooks.min.js
RuanjianshejiDeZhexue/js/hooks.min.map
RuanjianshejiDeZhexue/js/reader.js
RuanjianshejiDeZhexue/js/reader.js.map
RuanjianshejiDeZhexue/js/reader.min.js
RuanjianshejiDeZhexue/js/reader.min.map
RuanjianshejiDeZhexue/js/hooks/__init__.py
RuanjianshejiDeZhexue/js/hooks/extensions/__init__.py
RuanjianshejiDeZhexue/js/hooks/extensions/highlight.js
RuanjianshejiDeZhexue/js/libs/__init__.py
RuanjianshejiDeZhexue/js/libs/jquery.min.js
RuanjianshejiDeZhexue/js/libs/localforage.min.js
RuanjianshejiDeZhexue/js/libs/screenfull.js
RuanjianshejiDeZhexue/js/libs/screenfull.min.js
RuanjianshejiDeZhexue/js/libs/zip.min.js
RuanjianshejiDeZhexue/js/plugins/__init__.py
ruanjiansheji_de_zhexue-2024.3.5.0.dist-info/METADATA
ruanjiansheji_de_zhexue-2024.3.5.0.dist-info/WHEEL
ruanjiansheji_de_zhexue-2024.3.5.0.dist-info/entry_points.txt
ruanjiansheji_de_zhexue-2024.3.5.0.dist-info/top_level.txt
ruanjiansheji_de_zhexue-2024.3.5.0.dist-info/RECORD
